ereuse_utils/__init__.py
ereuse_utils/cli.py
ereuse_utils/cmd.py
ereuse_utils/getter.py
ereuse_utils/naming.py
ereuse_utils/nested_lookup.py
ereuse_utils/session.py
ereuse_utils/test.py
ereuse_utils/text.py
ereuse_utils/usb_flash_drive.py
ereuse_utils-0.4.0b50.dist-info/LICENSE.txt
ereuse_utils-0.4.0b50.dist-info/METADATA
ereuse_utils-0.4.0b50.dist-info/WHEEL
ereuse_utils-0.4.0b50.dist-info/top_level.txt
ereuse_utils-0.4.0b50.dist-info/RECORD
